ComfyUI_Ib_CustomNodes/.gitignore
ComfyUI_Ib_CustomNodes/LICENSE.txt
ComfyUI_Ib_CustomNodes/__init__.py
ComfyUI_Ib_CustomNodes/image.py
ComfyUI_Ib_CustomNodes/pyproject.toml
ComfyUI_Ib_CustomNodes/requirements.txt
ComfyUI_Ib_CustomNodes/usage.jpg
comfyui_ib_customnodes-0.2.3.dist-info/METADATA
comfyui_ib_customnodes-0.2.3.dist-info/WHEEL
comfyui_ib_customnodes-0.2.3.dist-info/entry_points.txt
comfyui_ib_customnodes-0.2.3.dist-info/licenses/LICENSE.txt
comfyui_ib_customnodes-0.2.3.dist-info/RECORD
