Metadata-Version: 2.4
Name: ComfyUI_Ib_CustomNodes
Version: 0.2.3
Summary: Load Image From Path, PIL.Image
Project-URL: Homepage, https://github.com/Chaoses-Ib/ComfyUI_Ib_CustomNodes
Project-URL: comfyui-legacy, https://github.com/Chaoses-Ib/comfyui-legacy
License-Expression: MIT
License-File: LICENSE.txt
Keywords: comfyui
